[
  {
    "zone": "Stor-Oslo",
    "municipality": "Oslo",
    "area": "Oslo",
    "station": "Kirkeveien",
    "eoi": "NO0011A",
    "component": "CO",
    "fromTime": "2019-04-25T00:00:00+01:00",
    "toTime": "2019-04-25T01:00:00+01:00",
    "value": 0.223987,
    "unit": "mg/m³",
    "latitude": 59.93233,
    "longitude": 10.72447,
    "timestep": 3600,
    "index": 1,
    "color": "6ee86e"
  },
  {
    "zone": "Stor-Oslo",
    "municipality": "Oslo",
    "area": "Oslo",
    "station": "Sofienbergparken",
    "eoi": "NO0073A",
    "component": "SO2",
    "fromTime": "2019-04-25T00:00:00+01:00",
    "toTime": "2019-04-25T01:00:00+01:00",
    "value": 1.951059,
    "unit": "µg/m³",
    "latitude": 59.92295,
    "longitude": 10.76573,
    "timestep": 3600,
    "index": 1,
    "color": "6ee86e"
  },
  {
    "zone": "Øst og Sørlandet",
    "municipality": "Grenland",
    "area": "Grenland",
    "station": "Furulund",
    "eoi": "NO0115A",
    "component": "SO2",
    "fromTime": "2019-04-25T00:00:00+01:00",
    "toTime": "2019-04-25T01:00:00+01:00",
    "value": 0.551981,
    "unit": "µg/m³",
    "latitude": 59.057304,
    "longitude": 9.695568,
    "timestep": 3600,
    "index": 1,
    "color": "6ee86e"
  },
  {
    "zone": "Øst og Sørlandet",
    "municipality": "Lillesand",
    "area": "Lillesand",
    "station": "Holta",
    "eoi": "NO0100A",
    "component": "SO2",
    "fromTime": "2019-04-25T00:00:00+01:00",
    "toTime": "2019-04-25T01:00:00+01:00",
    "value": 1.32006,
    "unit": "µg/m³",
    "latitude": 58.25602,
    "longitude": 8.35935,
    "timestep": 3600,
    "index": 1,
    "color": "6ee86e"
  },
  {
    "zone": "Troms og Finnmark",
    "municipality": "Sør-Varanger",
    "area": "Sør-Varanger",
    "station": "Svanvik",
    "eoi": "NO0047R",
    "component": "SO2",
    "fromTime": "2019-04-25T00:00:00+01:00",
    "toTime": "2019-04-25T01:00:00+01:00",
    "value": 0.549417,
    "unit": "µg/m³",
    "latitude": 69.45505,
    "longitude": 30.04075,
    "timestep": 3600,
    "index": 1,
    "color": "6ee86e"
  },
  {
    "zone": "Øst og Sørlandet",
    "municipality": "Sarpsborg",
    "area": "Sarpsborg",
    "station": "Vollgata",
    "eoi": "NO0098A",
    "component": "SO2",
    "fromTime": "2019-04-25T00:00:00+01:00",
    "toTime": "2019-04-25T01:00:00+01:00",
    "value": 11.776822,
    "unit": "µg/m³",
    "latitude": 59.27897,
    "longitude": 11.12228,
    "timestep": 3600,
    "index": 1,
    "color": "6ee86e"
  },
  {
    "zone": "Troms og Finnmark",
    "municipality": "Sør-Varanger",
    "area": "Sør-Varanger",
    "station": "Karpdalen",
    "eoi": "NO0094A",
    "component": "SO2",
    "fromTime": "2019-04-25T00:00:00+01:00",
    "toTime": "2019-04-25T01:00:00+01:00",
    "value": -2.843702,
    "unit": "µg/m³",
    "latitude": 69.65617,
    "longitude": 30.42147,
    "timestep": 3600,
    "index": 1,
    "color": "6ee86e"
  },
  {
    "zone": "Stor-Oslo",
    "municipality": "Oslo",
    "area": "Oslo",
    "station": "Bryn skole",
    "eoi": null,
    "component": "PM10",
    "fromTime": "2019-04-25T01:00:00+01:00",
    "toTime": "2019-04-25T02:00:00+01:00",
    "value": 52.240778,
    "unit": "µg/m³",
    "latitude": 59.914106,
    "longitude": 10.82263,
    "timestep": 3600,
    "index": 1,
    "color": "6ee86e"
  },
  {
    "zone": "Vestlandet",
    "municipality": "Stavanger",
    "area": "Stavanger",
    "station": "Schancheholen",
    "eoi": "NO0125A",
    "component": "PM10",
    "fromTime": "2019-04-25T00:00:00+01:00",
    "toTime": "2019-04-25T01:00:00+01:00",
    "value": 19.782333,
    "unit": "µg/m³",
    "latitude": 58.951877,
    "longitude": 5.721875,
    "timestep": 3600,
    "index": 1,
    "color": "6ee86e"
  },
  {
    "zone": "Troms og Finnmark",
    "municipality": "Tromsø",
    "area": "Tromsø",
    "station": "Rambergan",
    "eoi": "NO0124A",
    "component": "PM10",
    "fromTime": "2019-04-25T00:00:00+01:00",
    "toTime": "2019-04-25T01:00:00+01:00",
    "value": 23.65,
    "unit": "µg/m³",
    "latitude": 69.65428,
    "longitude": 18.95636,
    "timestep": 3600,
    "index": 1,
    "color": "6ee86e"
  },
  {
    "zone": "Øst og Sørlandet",
    "municipality": "N/A",
    "area": "Brumunddal",
    "station": "Ringsakervegen",
    "eoi": null,
    "component": "PM10",
    "fromTime": "2019-04-25T00:00:00+01:00",
    "toTime": "2019-04-25T01:00:00+01:00",
    "value": 56,
    "unit": "µg/m³",
    "latitude": 60.88593,
    "longitude": 10.93785,
    "timestep": 3600,
    "index": 1,
    "color": "6ee86e"
  },
  {
    "zone": "Øst og Sørlandet",
    "municipality": "Tønsberg",
    "area": "Tønsberg",
    "station": "Nedre Langgate",
    "eoi": null,
    "component": "PM10",
    "fromTime": "2019-04-25T00:00:00+01:00",
    "toTime": "2019-04-25T01:00:00+01:00",
    "value": 34.155483,
    "unit": "µg/m³",
    "latitude": 59.263725,
    "longitude": 10.411165,
    "timestep": 3600,
    "index": 1,
    "color": "6ee86e"
  },
  {
    "zone": "Stor-Oslo",
    "municipality": "Oslo",
    "area": "Oslo",
    "station": "E6 Alna senter",
    "eoi": "NO0122A",
    "component": "PM10",
    "fromTime": "2019-04-25T00:00:00+01:00",
    "toTime": "2019-04-25T01:00:00+01:00",
    "value": 50.703111,
    "unit": "µg/m³",
    "latitude": 59.92556,
    "longitude": 10.850367,
    "timestep": 3600,
    "index": 1,
    "color": "6ee86e"
  },
  {
    "zone": "Midt-Norge og Nordland",
    "municipality": "N/A",
    "area": "Bodø",
    "station": "Olav V gate",
    "eoi": null,
    "component": "PM10",
    "fromTime": "2019-04-25T00:00:00+01:00",
    "toTime": "2019-04-25T01:00:00+01:00",
    "value": 14.934042,
    "unit": "µg/m³",
    "latitude": 67.275501,
    "longitude": 14.419057,
    "timestep": 3600,
    "index": 1,
    "color": "6ee86e"
  },
  {
    "zone": "Troms og Finnmark",
    "municipality": "Harstad",
    "area": "Harstad",
    "station": "Seljestad Rv83",
    "eoi": null,
    "component": "PM10",
    "fromTime": "2019-04-25T00:00:00+01:00",
    "toTime": "2019-04-25T01:00:00+01:00",
    "value": 22.458111,
    "unit": "µg/m³",
    "latitude": 68.79222701,
    "longitude": 16.53742346,
    "timestep": 3600,
    "index": 1,
    "color": "6ee86e"
  },
  {
    "zone": "Midt-Norge og Nordland",
    "municipality": "Rana",
    "area": "Mo i Rana",
    "station": "Moheia Vest",
    "eoi": "NO0123A",
    "component": "PM10",
    "fromTime": "2019-04-25T00:00:00+01:00",
    "toTime": "2019-04-25T01:00:00+01:00",
    "value": 31.522639,
    "unit": "µg/m³",
    "latitude": 66.312191,
    "longitude": 14.149923,
    "timestep": 3600,
    "index": 1,
    "color": "6ee86e"
  },
  {
    "zone": "Øst og Sørlandet",
    "municipality": "Halden",
    "area": "Halden",
    "station": "Vaterland",
    "eoi": null,
    "component": "PM10",
    "fromTime": "2019-04-25T00:00:00+01:00",
    "toTime": "2019-04-25T01:00:00+01:00",
    "value": 46.6,
    "unit": "µg/m³",
    "latitude": 59.123314,
    "longitude": 11.391136,
    "timestep": 3600,
    "index": 1,
    "color": "6ee86e"
  },
  {
    "zone": "Øst og Sørlandet",
    "municipality": "Lørenskog",
    "area": "Lørenskog",
    "station": "Solheim",
    "eoi": null,
    "component": "PM10",
    "fromTime": "2019-04-25T00:00:00+01:00",
    "toTime": "2019-04-25T01:00:00+01:00",
    "value": 56.874889,
    "unit": "µg/m³",
    "latitude": 59.928612,
    "longitude": 10.953203,
    "timestep": 3600,
    "index": 1,
    "color": "6ee86e"
  },
  {
    "zone": "Øst og Sørlandet",
    "municipality": "Gjøvik",
    "area": "Gjøvik",
    "station": "Minnesundvegen, Gjøvik",
    "eoi": "NO0103A",
    "component": "PM10",
    "fromTime": "2019-04-25T00:00:00+01:00",
    "toTime": "2019-04-25T01:00:00+01:00",
    "value": 50.32679,
    "unit": "µg/m³",
    "latitude": 60.79089,
    "longitude": 10.6967,
    "timestep": 3600,
    "index": 1,
    "color": "6ee86e"
  },
  {
    "zone": "Bergen",
    "municipality": "Bergen",
    "area": "Bergen",
    "station": "Klosterhaugen",
    "eoi": "NO0120A",
    "component": "PM10",
    "fromTime": "2019-04-25T00:00:00+01:00",
    "toTime": "2019-04-25T01:00:00+01:00",
    "value": 14.603897,
    "unit": "µg/m³",
    "latitude": 60.395929,
    "longitude": 5.312674,
    "timestep": 3600,
    "index": 1,
    "color": "6ee86e"
  },
  {
    "zone": "Bergen",
    "municipality": "Bergen",
    "area": "Bergen",
    "station": "Rådal",
    "eoi": "NO0121A",
    "component": "PM10",
    "fromTime": "2019-04-25T00:00:00+01:00",
    "toTime": "2019-04-25T01:00:00+01:00",
    "value": 14.647547,
    "unit": "µg/m³",
    "latitude": 60.294268,
    "longitude": 5.324619,
    "timestep": 3600,
    "index": 1,
    "color": "6ee86e"
  },
  {
    "zone": "Øst og Sørlandet",
    "municipality": "Elverum",
    "area": "Elverum",
    "station": "Leiret",
    "eoi": "NO0119A",
    "component": "PM10",
    "fromTime": "2019-04-25T00:00:00+01:00",
    "toTime": "2019-04-25T01:00:00+01:00",
    "value": 46.688078,
    "unit": "µg/m³",
    "latitude": 60.88364255,
    "longitude": 11.55930063,
    "timestep": 3600,
    "index": 1,
    "color": "6ee86e"
  },
  {
    "zone": "Bergen",
    "municipality": "Bergen",
    "area": "Bergen",
    "station": "Rolland, Åsane",
    "eoi": "NO0108A",
    "component": "PM10",
    "fromTime": "2019-04-25T00:00:00+01:00",
    "toTime": "2019-04-25T01:00:00+01:00",
    "value": 15.233031,
    "unit": "µg/m³",
    "latitude": 60.462665,
    "longitude": 5.332447,
    "timestep": 3600,
    "index": 1,
    "color": "6ee86e"
  },
  {
    "zone": "Trondheim",
    "municipality": "Trondheim",
    "area": "Trondheim",
    "station": "Bakke kirke",
    "eoi": "NO0068A",
    "component": "PM10",
    "fromTime": "2019-04-25T00:00:00+01:00",
    "toTime": "2019-04-25T01:00:00+01:00",
    "value": 23.876666,
    "unit": "µg/m³",
    "latitude": 63.43293,
    "longitude": 10.41067,
    "timestep": 3600,
    "index": 1,
    "color": "6ee86e"
  },
  {
    "zone": "Stor-Oslo",
    "municipality": "Oslo",
    "area": "Oslo",
    "station": "Sofienbergparken",
    "eoi": "NO0073A",
    "component": "PM10",
    "fromTime": "2019-04-25T00:00:00+01:00",
    "toTime": "2019-04-25T01:00:00+01:00",
    "value": 45.4,
    "unit": "µg/m³",
    "latitude": 59.92295,
    "longitude": 10.76573,
    "timestep": 3600,
    "index": 1,
    "color": "6ee86e"
  },
  {
    "zone": "Øst og Sørlandet",
    "municipality": "Grenland",
    "area": "Grenland",
    "station": "Knarrdalstranda",
    "eoi": "NO0118A",
    "component": "PM10",
    "fromTime": "2019-04-25T00:00:00+01:00",
    "toTime": "2019-04-25T01:00:00+01:00",
    "value": 25.63,
    "unit": "µg/m³",
    "latitude": 59.13354,
    "longitude": 9.6219,
    "timestep": 3600,
    "index": 1,
    "color": "6ee86e"
  },
  {
    "zone": "Midt-Norge og Nordland",
    "municipality": "Ålesund",
    "area": "Ålesund",
    "station": "Karl Eriksens plass",
    "eoi": "NO0116A",
    "component": "PM10",
    "fromTime": "2019-04-25T00:00:00+01:00",
    "toTime": "2019-04-25T01:00:00+01:00",
    "value": 41.03,
    "unit": "µg/m³",
    "latitude": 62.470622,
    "longitude": 6.153501,
    "timestep": 3600,
    "index": 1,
    "color": "6ee86e"
  },
  {
    "zone": "Stor-Oslo",
    "municipality": "Oslo",
    "area": "Oslo",
    "station": "Åkebergveien",
    "eoi": null,
    "component": "PM10",
    "fromTime": "2019-04-25T00:00:00+01:00",
    "toTime": "2019-04-25T01:00:00+01:00",
    "value": 56,
    "unit": "µg/m³",
    "latitude": 59.912001,
    "longitude": 10.767426,
    "timestep": 3600,
    "index": 1,
    "color": "6ee86e"
  },
  {
    "zone": "Øst og Sørlandet",
    "municipality": "Grenland",
    "area": "Grenland",
    "station": "Furulund",
    "eoi": "NO0115A",
    "component": "PM10",
    "fromTime": "2019-04-25T00:00:00+01:00",
    "toTime": "2019-04-25T01:00:00+01:00",
    "value": 28.594269,
    "unit": "µg/m³",
    "latitude": 59.057304,
    "longitude": 9.695568,
    "timestep": 3600,
    "index": 1,
    "color": "6ee86e"
  },
  {
    "zone": "Bergen",
    "municipality": "Bergen",
    "area": "Bergen",
    "station": "Loddefjord",
    "eoi": "NO0109A",
    "component": "PM10",
    "fromTime": "2019-04-25T00:00:00+01:00",
    "toTime": "2019-04-25T01:00:00+01:00",
    "value": 13.918506,
    "unit": "µg/m³",
    "latitude": 60.361135,
    "longitude": 5.23686,
    "timestep": 3600,
    "index": 1,
    "color": "6ee86e"
  },
  {
    "zone": "Øst og Sørlandet",
    "municipality": "Sarpsborg",
    "area": "Sarpsborg",
    "station": "Alvim",
    "eoi": "NO0110A",
    "component": "PM10",
    "fromTime": "2019-04-25T00:00:00+01:00",
    "toTime": "2019-04-25T01:00:00+01:00",
    "value": 48.3,
    "unit": "µg/m³",
    "latitude": 59.27377544,
    "longitude": 11.08919017,
    "timestep": 3600,
    "index": 1,
    "color": "6ee86e"
  },
  {
    "zone": "Stor-Oslo",
    "municipality": "Bærum",
    "area": "Bærum",
    "station": "Eilif Dues vei",
    "eoi": "NO0099A",
    "component": "PM10",
    "fromTime": "2019-04-25T00:00:00+01:00",
    "toTime": "2019-04-25T01:00:00+01:00",
    "value": 50.6,
    "unit": "µg/m³",
    "latitude": 59.90608,
    "longitude": 10.61195,
    "timestep": 3600,
    "index": 1,
    "color": "6ee86e"
  },
  {
    "zone": "Stor-Oslo",
    "municipality": "Skedsmo",
    "area": "Lillestrøm",
    "station": "Vigernes",
    "eoi": "NO0111A",
    "component": "PM10",
    "fromTime": "2019-04-25T00:00:00+01:00",
    "toTime": "2019-04-25T01:00:00+01:00",
    "value": 24.455606,
    "unit": "µg/m³",
    "latitude": 59.955477,
    "longitude": 11.073983,
    "timestep": 3600,
    "index": 1,
    "color": "6ee86e"
  },
  {
    "zone": "Øst og Sørlandet",
    "municipality": "Hamar",
    "area": "Hamar",
    "station": "Vangsveien, Hamar",
    "eoi": "NO0104A",
    "component": "PM10",
    "fromTime": "2019-04-25T00:00:00+01:00",
    "toTime": "2019-04-25T01:00:00+01:00",
    "value": 39.296018,
    "unit": "µg/m³",
    "latitude": 60.79646,
    "longitude": 11.09777,
    "timestep": 3600,
    "index": 1,
    "color": "6ee86e"
  },
  {
    "zone": "Trondheim",
    "municipality": "Trondheim",
    "area": "Trondheim",
    "station": "Elgeseter",
    "eoi": "NO0060A",
    "component": "PM10",
    "fromTime": "2019-04-25T00:00:00+01:00",
    "toTime": "2019-04-25T01:00:00+01:00",
    "value": 23.839165,
    "unit": "µg/m³",
    "latitude": 63.419239,
    "longitude": 10.395945,
    "timestep": 3600,
    "index": 1,
    "color": "6ee86e"
  },
  {
    "zone": "Øst og Sørlandet",
    "municipality": "Fredrikstad",
    "area": "Fredrikstad",
    "station": "Nygaardsgata",
    "eoi": "NO0105A",
    "component": "PM10",
    "fromTime": "2019-04-25T00:00:00+01:00",
    "toTime": "2019-04-25T01:00:00+01:00",
    "value": 2.296044,
    "unit": "µg/m³",
    "latitude": 59.210191,
    "longitude": 10.940097,
    "timestep": 3600,
    "index": 1,
    "color": "6ee86e"
  },
  {
    "zone": "Trondheim",
    "municipality": "Trondheim",
    "area": "Trondheim",
    "station": "E6-Tiller",
    "eoi": "NO0102A",
    "component": "PM10",
    "fromTime": "2019-04-25T00:00:00+01:00",
    "toTime": "2019-04-25T01:00:00+01:00",
    "value": 31.110149,
    "unit": "µg/m³",
    "latitude": 63.3576,
    "longitude": 10.3719,
    "timestep": 3600,
    "index": 1,
    "color": "6ee86e"
  },
  {
    "zone": "Stor-Oslo",
    "municipality": "Oslo",
    "area": "Oslo",
    "station": "Rv 4, Aker sykehus",
    "eoi": "NO0101A",
    "component": "PM10",
    "fromTime": "2019-04-25T00:00:00+01:00",
    "toTime": "2019-04-25T01:00:00+01:00",
    "value": 47.364595,
    "unit": "µg/m³",
    "latitude": 59.94103,
    "longitude": 10.79803,
    "timestep": 3600,
    "index": 1,
    "color": "6ee86e"
  },
  {
    "zone": "Øst og Sørlandet",
    "municipality": "Kristiansand",
    "area": "Kristiansand",
    "station": "Gartnerløkka",
    "eoi": "NO0092A",
    "component": "PM10",
    "fromTime": "2019-04-25T00:00:00+01:00",
    "toTime": "2019-04-25T01:00:00+01:00",
    "value": 16.216667,
    "unit": "µg/m³",
    "latitude": 58.14703,
    "longitude": 7.98662,
    "timestep": 3600,
    "index": 1,
    "color": "6ee86e"
  },
  {
    "zone": "Øst og Sørlandet",
    "municipality": "Moss",
    "area": "Moss",
    "station": "Kransen",
    "eoi": "NO0112A",
    "component": "PM10",
    "fromTime": "2019-04-25T00:00:00+01:00",
    "toTime": "2019-04-25T01:00:00+01:00",
    "value": 41.876333,
    "unit": "µg/m³",
    "latitude": 59.433471,
    "longitude": 10.66176236,
    "timestep": 3600,
    "index": 1,
    "color": "6ee86e"
  },
  {
    "zone": "Stor-Oslo",
    "municipality": "Oslo",
    "area": "Oslo",
    "station": "Kirkeveien",
    "eoi": "NO0011A",
    "component": "PM10",
    "fromTime": "2019-04-25T00:00:00+01:00",
    "toTime": "2019-04-25T01:00:00+01:00",
    "value": 42.119856,
    "unit": "µg/m³",
    "latitude": 59.93233,
    "longitude": 10.72447,
    "timestep": 3600,
    "index": 1,
    "color": "6ee86e"
  },
  {
    "zone": "Øst og Sørlandet",
    "municipality": "Kristiansand",
    "area": "Kristiansand",
    "station": "Stener Heyerdahl",
    "eoi": "NO0063A",
    "component": "PM10",
    "fromTime": "2019-04-25T00:00:00+01:00",
    "toTime": "2019-04-25T01:00:00+01:00",
    "value": 17,
    "unit": "µg/m³",
    "latitude": 58.14888,
    "longitude": 7.99183,
    "timestep": 3600,
    "index": 1,
    "color": "6ee86e"
  },
  {
    "zone": "Stor-Oslo",
    "municipality": "Oslo",
    "area": "Oslo",
    "station": "Manglerud",
    "eoi": "NO0071A",
    "component": "PM10",
    "fromTime": "2019-04-25T00:00:00+01:00",
    "toTime": "2019-04-25T01:00:00+01:00",
    "value": 47.96,
    "unit": "µg/m³",
    "latitude": 59.89869,
    "longitude": 10.81495,
    "timestep": 3600,
    "index": 1,
    "color": "6ee86e"
  },
  {
    "zone": "Øst og Sørlandet",
    "municipality": "Lillehammer",
    "area": "Lillehammer",
    "station": "Lillehammer barnehage",
    "eoi": "NO0075A",
    "component": "PM10",
    "fromTime": "2019-04-25T00:00:00+01:00",
    "toTime": "2019-04-25T01:00:00+01:00",
    "value": 32.921167,
    "unit": "µg/m³",
    "latitude": 61.12087,
    "longitude": 10.46563,
    "timestep": 3600,
    "index": 1,
    "color": "6ee86e"
  },
  {
    "zone": "Øst og Sørlandet",
    "municipality": "Lillehammer",
    "area": "Lillehammer",
    "station": "Bankplassen",
    "eoi": "NO0074A",
    "component": "PM10",
    "fromTime": "2019-04-25T00:00:00+01:00",
    "toTime": "2019-04-25T01:00:00+01:00",
    "value": 40.81,
    "unit": "µg/m³",
    "latitude": 61.11288,
    "longitude": 10.46497,
    "timestep": 3600,
    "index": 1,
    "color": "6ee86e"
  },
  {
    "zone": "Midt-Norge og Nordland",
    "municipality": "Ålesund",
    "area": "Ålesund",
    "station": "Grimmerhaugen",
    "eoi": "NO0070A",
    "component": "PM10",
    "fromTime": "2019-04-25T00:00:00+01:00",
    "toTime": "2019-04-25T01:00:00+01:00",
    "value": 34.87,
    "unit": "µg/m³",
    "latitude": 62.47217,
    "longitude": 6.15682,
    "timestep": 3600,
    "index": 1,
    "color": "6ee86e"
  },
  {
    "zone": "Bergen",
    "municipality": "Bergen",
    "area": "Bergen",
    "station": "Danmarks plass",
    "eoi": "NO0059A",
    "component": "PM10",
    "fromTime": "2019-04-25T00:00:00+01:00",
    "toTime": "2019-04-25T01:00:00+01:00",
    "value": 14.349994,
    "unit": "µg/m³",
    "latitude": 60.37408,
    "longitude": 5.34042,
    "timestep": 3600,
    "index": 1,
    "color": "6ee86e"
  },
  {
    "zone": "Øst og Sørlandet",
    "municipality": "Grenland",
    "area": "Grenland",
    "station": "Lensmannsdalen",
    "eoi": "NO0061A",
    "component": "PM10",
    "fromTime": "2019-04-25T00:00:00+01:00",
    "toTime": "2019-04-25T01:00:00+01:00",
    "value": 39.6,
    "unit": "µg/m³",
    "latitude": 59.15927,
    "longitude": 9.63565,
    "timestep": 3600,
    "index": 1,
    "color": "6ee86e"
  },
  {
    "zone": "Stor-Oslo",
    "municipality": "Drammen",
    "area": "Drammen",
    "station": "Bangeløkka",
    "eoi": "NO0067A",
    "component": "PM10",
    "fromTime": "2019-04-25T00:00:00+01:00",
    "toTime": "2019-04-25T01:00:00+01:00",
    "value": 33,
    "unit": "µg/m³",
    "latitude": 59.73325,
    "longitude": 10.21187,
    "timestep": 3600,
    "index": 1,
    "color": "6ee86e"
  },
  {
    "zone": "Stor-Oslo",
    "municipality": "Oslo",
    "area": "Oslo",
    "station": "Skøyen",
    "eoi": "NO0072A",
    "component": "PM10",
    "fromTime": "2019-04-25T00:00:00+01:00",
    "toTime": "2019-04-25T01:00:00+01:00",
    "value": 59,
    "unit": "µg/m³",
    "latitude": 59.91975,
    "longitude": 10.68973,
    "timestep": 3600,
    "index": 1,
    "color": "6ee86e"
  },
  {
    "zone": "Øst og Sørlandet",
    "municipality": "Fredrikstad",
    "area": "Fredrikstad",
    "station": "St.Croix",
    "eoi": "NO0084A",
    "component": "PM10",
    "fromTime": "2019-04-25T00:00:00+01:00",
    "toTime": "2019-04-25T01:00:00+01:00",
    "value": 29.2,
    "unit": "µg/m³",
    "latitude": 59.2103,
    "longitude": 10.9454,
    "timestep": 3600,
    "index": 1,
    "color": "6ee86e"
  },
  {
    "zone": "Stor-Oslo",
    "municipality": "Oslo",
    "area": "Oslo",
    "station": "Smestad",
    "eoi": "NO0095A",
    "component": "PM10",
    "fromTime": "2019-04-25T00:00:00+01:00",
    "toTime": "2019-04-25T01:00:00+01:00",
    "value": 43.021006,
    "unit": "µg/m³",
    "latitude": 59.93255,
    "longitude": 10.66984,
    "timestep": 3600,
    "index": 1,
    "color": "6ee86e"
  },
  {
    "zone": "Øst og Sørlandet",
    "municipality": "Grenland",
    "area": "Grenland",
    "station": "Sverresgate",
    "eoi": "NO0106A",
    "component": "PM10",
    "fromTime": "2019-04-25T00:00:00+01:00",
    "toTime": "2019-04-25T01:00:00+01:00",
    "value": 30.47,
    "unit": "µg/m³",
    "latitude": 59.13812,
    "longitude": 9.65212,
    "timestep": 3600,
    "index": 1,
    "color": "6ee86e"
  },
  {
    "zone": "Vestlandet",
    "municipality": "Stavanger",
    "area": "Stavanger",
    "station": "Våland",
    "eoi": "NO0065A",
    "component": "PM10",
    "fromTime": "2019-04-25T00:00:00+01:00",
    "toTime": "2019-04-25T01:00:00+01:00",
    "value": 17.851028,
    "unit": "µg/m³",
    "latitude": 58.96173,
    "longitude": 5.73147,
    "timestep": 3600,
    "index": 1,
    "color": "6ee86e"
  },
  {
    "zone": "Vestlandet",
    "municipality": "Stavanger",
    "area": "Stavanger",
    "station": "Kannik",
    "eoi": "NO0076A",
    "component": "PM10",
    "fromTime": "2019-04-25T00:00:00+01:00",
    "toTime": "2019-04-25T01:00:00+01:00",
    "value": 17.7,
    "unit": "µg/m³",
    "latitude": 58.96415,
    "longitude": 5.72785,
    "timestep": 3600,
    "index": 1,
    "color": "6ee86e"
  },
  {
    "zone": "Øst og Sørlandet",
    "municipality": "N/A",
    "area": "Hønefoss",
    "station": "Hønefoss skole",
    "eoi": null,
    "component": "PM10",
    "fromTime": "2019-04-25T00:00:00+01:00",
    "toTime": "2019-04-25T01:00:00+01:00",
    "value": 63.7,
    "unit": "µg/m³",
    "latitude": 60.170873,
    "longitude": 10.261552,
    "timestep": 3600,
    "index": 2,
    "color": "ff9900"
  },
  {
    "zone": "Stor-Oslo",
    "municipality": "Oslo",
    "area": "Oslo",
    "station": "Hjortnes",
    "eoi": "NO0093A",
    "component": "PM10",
    "fromTime": "2019-04-25T00:00:00+01:00",
    "toTime": "2019-04-25T01:00:00+01:00",
    "value": 61.6,
    "unit": "µg/m³",
    "latitude": 59.91132,
    "longitude": 10.70407,
    "timestep": 3600,
    "index": 2,
    "color": "ff9900"
  },
  {
    "zone": "Troms og Finnmark",
    "municipality": "Tromsø",
    "area": "Tromsø",
    "station": "Hansjordnesbukta",
    "eoi": "NO0079A",
    "component": "PM10",
    "fromTime": "2019-04-25T00:00:00+01:00",
    "toTime": "2019-04-25T01:00:00+01:00",
    "value": 78.65,
    "unit": "µg/m³",
    "latitude": 69.65625,
    "longitude": 18.96372,
    "timestep": 3600,
    "index": 2,
    "color": "ff9900"
  },
  {
    "zone": "Midt-Norge og Nordland",
    "municipality": "Narvik",
    "area": "Narvik",
    "station": "Sentrum",
    "eoi": "NO0113A",
    "component": "PM10",
    "fromTime": "2019-04-25T00:00:00+01:00",
    "toTime": "2019-04-25T01:00:00+01:00",
    "value": 74.221344,
    "unit": "µg/m³",
    "latitude": 68.435397,
    "longitude": 17.424891,
    "timestep": 3600,
    "index": 2,
    "color": "ff9900"
  },
  {
    "zone": "Stor-Oslo",
    "municipality": "Bærum",
    "area": "Bærum",
    "station": "Bekkestua",
    "eoi": "NO0114A",
    "component": "PM10",
    "fromTime": "2019-04-25T00:00:00+01:00",
    "toTime": "2019-04-25T01:00:00+01:00",
    "value": 60,
    "unit": "µg/m³",
    "latitude": 59.9181,
    "longitude": 10.5839,
    "timestep": 3600,
    "index": 2,
    "color": "ff9900"
  },
  {
    "zone": "Stor-Oslo",
    "municipality": "Oslo",
    "area": "Oslo",
    "station": "Bygdøy Alle",
    "eoi": "NO0083A",
    "component": "PM10",
    "fromTime": "2019-04-25T00:00:00+01:00",
    "toTime": "2019-04-25T01:00:00+01:00",
    "value": 66.5,
    "unit": "µg/m³",
    "latitude": 59.91898,
    "longitude": 10.69707,
    "timestep": 3600,
    "index": 2,
    "color": "ff9900"
  },
  {
    "zone": "Stor-Oslo",
    "municipality": "Oslo",
    "area": "Oslo",
    "station": "Bryn skole",
    "eoi": null,
    "component": "PM2.5",
    "fromTime": "2019-04-25T01:00:00+01:00",
    "toTime": "2019-04-25T02:00:00+01:00",
    "value": 27.0985,
    "unit": "µg/m³",
    "latitude": 59.914106,
    "longitude": 10.82263,
    "timestep": 3600,
    "index": 1,
    "color": "6ee86e"
  },
  {
    "zone": "Vestlandet",
    "municipality": "Stavanger",
    "area": "Stavanger",
    "station": "Schancheholen",
    "eoi": "NO0125A",
    "component": "PM2.5",
    "fromTime": "2019-04-25T00:00:00+01:00",
    "toTime": "2019-04-25T01:00:00+01:00",
    "value": 17.378889,
    "unit": "µg/m³",
    "latitude": 58.951877,
    "longitude": 5.721875,
    "timestep": 3600,
    "index": 1,
    "color": "6ee86e"
  },
  {
    "zone": "Øst og Sørlandet",
    "municipality": "N/A",
    "area": "Hønefoss",
    "station": "Hønefoss skole",
    "eoi": null,
    "component": "PM2.5",
    "fromTime": "2019-04-25T00:00:00+01:00",
    "toTime": "2019-04-25T01:00:00+01:00",
    "value": 28.6,
    "unit": "µg/m³",
    "latitude": 60.170873,
    "longitude": 10.261552,
    "timestep": 3600,
    "index": 1,
    "color": "6ee86e"
  },
  {
    "zone": "Midt-Norge og Nordland",
    "municipality": "Rana",
    "area": "Mo i Rana",
    "station": "Moheia Vest",
    "eoi": "NO0123A",
    "component": "PM2.5",
    "fromTime": "2019-04-25T00:00:00+01:00",
    "toTime": "2019-04-25T01:00:00+01:00",
    "value": 9.247222,
    "unit": "µg/m³",
    "latitude": 66.312191,
    "longitude": 14.149923,
    "timestep": 3600,
    "index": 1,
    "color": "6ee86e"
  },
  {
    "zone": "Øst og Sørlandet",
    "municipality": "N/A",
    "area": "Brumunddal",
    "station": "Ringsakervegen",
    "eoi": null,
    "component": "PM2.5",
    "fromTime": "2019-04-25T00:00:00+01:00",
    "toTime": "2019-04-25T01:00:00+01:00",
    "value": 26.3,
    "unit": "µg/m³",
    "latitude": 60.88593,
    "longitude": 10.93785,
    "timestep": 3600,
    "index": 1,
    "color": "6ee86e"
  },
  {
    "zone": "Øst og Sørlandet",
    "municipality": "Tønsberg",
    "area": "Tønsberg",
    "station": "Nedre Langgate",
    "eoi": null,
    "component": "PM2.5",
    "fromTime": "2019-04-25T00:00:00+01:00",
    "toTime": "2019-04-25T01:00:00+01:00",
    "value": 16.649181,
    "unit": "µg/m³",
    "latitude": 59.263725,
    "longitude": 10.411165,
    "timestep": 3600,
    "index": 1,
    "color": "6ee86e"
  },
  {
    "zone": "Midt-Norge og Nordland",
    "municipality": "N/A",
    "area": "Bodø",
    "station": "Olav V gate",
    "eoi": null,
    "component": "PM2.5",
    "fromTime": "2019-04-25T00:00:00+01:00",
    "toTime": "2019-04-25T01:00:00+01:00",
    "value": 9.877994,
    "unit": "µg/m³",
    "latitude": 67.275501,
    "longitude": 14.419057,
    "timestep": 3600,
    "index": 1,
    "color": "6ee86e"
  },
  {
    "zone": "Troms og Finnmark",
    "municipality": "Harstad",
    "area": "Harstad",
    "station": "Seljestad Rv83",
    "eoi": null,
    "component": "PM2.5",
    "fromTime": "2019-04-25T00:00:00+01:00",
    "toTime": "2019-04-25T01:00:00+01:00",
    "value": 15.235889,
    "unit": "µg/m³",
    "latitude": 68.79222701,
    "longitude": 16.53742346,
    "timestep": 3600,
    "index": 1,
    "color": "6ee86e"
  },
  {
    "zone": "Øst og Sørlandet",
    "municipality": "Fredrikstad",
    "area": "Fredrikstad",
    "station": "Nygaardsgata",
    "eoi": "NO0105A",
    "component": "PM2.5",
    "fromTime": "2019-04-25T00:00:00+01:00",
    "toTime": "2019-04-25T01:00:00+01:00",
    "value": 0.569933,
    "unit": "µg/m³",
    "latitude": 59.210191,
    "longitude": 10.940097,
    "timestep": 3600,
    "index": 1,
    "color": "6ee86e"
  },
  {
    "zone": "Øst og Sørlandet",
    "municipality": "Halden",
    "area": "Halden",
    "station": "Vaterland",
    "eoi": null,
    "component": "PM2.5",
    "fromTime": "2019-04-25T00:00:00+01:00",
    "toTime": "2019-04-25T01:00:00+01:00",
    "value": 22.1,
    "unit": "µg/m³",
    "latitude": 59.123314,
    "longitude": 11.391136,
    "timestep": 3600,
    "index": 1,
    "color": "6ee86e"
  },
  {
    "zone": "Øst og Sørlandet",
    "municipality": "Lørenskog",
    "area": "Lørenskog",
    "station": "Solheim",
    "eoi": null,
    "component": "PM2.5",
    "fromTime": "2019-04-25T00:00:00+01:00",
    "toTime": "2019-04-25T01:00:00+01:00",
    "value": 28.148056,
    "unit": "µg/m³",
    "latitude": 59.928612,
    "longitude": 10.953203,
    "timestep": 3600,
    "index": 1,
    "color": "6ee86e"
  },
  {
    "zone": "Øst og Sørlandet",
    "municipality": "Sarpsborg",
    "area": "Sarpsborg",
    "station": "Alvim",
    "eoi": "NO0110A",
    "component": "PM2.5",
    "fromTime": "2019-04-25T00:00:00+01:00",
    "toTime": "2019-04-25T01:00:00+01:00",
    "value": 24,
    "unit": "µg/m³",
    "latitude": 59.27377544,
    "longitude": 11.08919017,
    "timestep": 3600,
    "index": 1,
    "color": "6ee86e"
  },
  {
    "zone": "Bergen",
    "municipality": "Bergen",
    "area": "Bergen",
    "station": "Klosterhaugen",
    "eoi": "NO0120A",
    "component": "PM2.5",
    "fromTime": "2019-04-25T00:00:00+01:00",
    "toTime": "2019-04-25T01:00:00+01:00",
    "value": 10.978436,
    "unit": "µg/m³",
    "latitude": 60.395929,
    "longitude": 5.312674,
    "timestep": 3600,
    "index": 1,
    "color": "6ee86e"
  },
  {
    "zone": "Bergen",
    "municipality": "Bergen",
    "area": "Bergen",
    "station": "Rådal",
    "eoi": "NO0121A",
    "component": "PM2.5",
    "fromTime": "2019-04-25T00:00:00+01:00",
    "toTime": "2019-04-25T01:00:00+01:00",
    "value": 11.100667,
    "unit": "µg/m³",
    "latitude": 60.294268,
    "longitude": 5.324619,
    "timestep": 3600,
    "index": 1,
    "color": "6ee86e"
  },
  {
    "zone": "Øst og Sørlandet",
    "municipality": "Hamar",
    "area": "Hamar",
    "station": "Vangsveien, Hamar",
    "eoi": "NO0104A",
    "component": "PM2.5",
    "fromTime": "2019-04-25T00:00:00+01:00",
    "toTime": "2019-04-25T01:00:00+01:00",
    "value": 19.135458,
    "unit": "µg/m³",
    "latitude": 60.79646,
    "longitude": 11.09777,
    "timestep": 3600,
    "index": 1,
    "color": "6ee86e"
  },
  {
    "zone": "Stor-Oslo",
    "municipality": "Oslo",
    "area": "Oslo",
    "station": "Smestad",
    "eoi": "NO0095A",
    "component": "PM2.5",
    "fromTime": "2019-04-25T00:00:00+01:00",
    "toTime": "2019-04-25T01:00:00+01:00",
    "value": 21.180139,
    "unit": "µg/m³",
    "latitude": 59.93255,
    "longitude": 10.66984,
    "timestep": 3600,
    "index": 1,
    "color": "6ee86e"
  },
  {
    "zone": "Stor-Oslo",
    "municipality": "Oslo",
    "area": "Oslo",
    "station": "Sofienbergparken",
    "eoi": "NO0073A",
    "component": "PM2.5",
    "fromTime": "2019-04-25T00:00:00+01:00",
    "toTime": "2019-04-25T01:00:00+01:00",
    "value": 27,
    "unit": "µg/m³",
    "latitude": 59.92295,
    "longitude": 10.76573,
    "timestep": 3600,
    "index": 1,
    "color": "6ee86e"
  },
  {
    "zone": "Vestlandet",
    "municipality": "Stavanger",
    "area": "Stavanger",
    "station": "Våland",
    "eoi": "NO0065A",
    "component": "PM2.5",
    "fromTime": "2019-04-25T00:00:00+01:00",
    "toTime": "2019-04-25T01:00:00+01:00",
    "value": 13.919086,
    "unit": "µg/m³",
    "latitude": 58.96173,
    "longitude": 5.73147,
    "timestep": 3600,
    "index": 1,
    "color": "6ee86e"
  },
  {
    "zone": "Øst og Sørlandet",
    "municipality": "Elverum",
    "area": "Elverum",
    "station": "Leiret",
    "eoi": "NO0119A",
    "component": "PM2.5",
    "fromTime": "2019-04-25T00:00:00+01:00",
    "toTime": "2019-04-25T01:00:00+01:00",
    "value": 20.209714,
    "unit": "µg/m³",
    "latitude": 60.88364255,
    "longitude": 11.55930063,
    "timestep": 3600,
    "index": 1,
    "color": "6ee86e"
  },
  {
    "zone": "Øst og Sørlandet",
    "municipality": "Grenland",
    "area": "Grenland",
    "station": "Knarrdalstranda",
    "eoi": "NO0118A",
    "component": "PM2.5",
    "fromTime": "2019-04-25T00:00:00+01:00",
    "toTime": "2019-04-25T01:00:00+01:00",
    "value": 13.8,
    "unit": "µg/m³",
    "latitude": 59.13354,
    "longitude": 9.6219,
    "timestep": 3600,
    "index": 1,
    "color": "6ee86e"
  },
  {
    "zone": "Øst og Sørlandet",
    "municipality": "Grenland",
    "area": "Grenland",
    "station": "Furulund",
    "eoi": "NO0115A",
    "component": "PM2.5",
    "fromTime": "2019-04-25T00:00:00+01:00",
    "toTime": "2019-04-25T01:00:00+01:00",
    "value": 15.182514,
    "unit": "µg/m³",
    "latitude": 59.057304,
    "longitude": 9.695568,
    "timestep": 3600,
    "index": 1,
    "color": "6ee86e"
  },
  {
    "zone": "Midt-Norge og Nordland",
    "municipality": "Narvik",
    "area": "Narvik",
    "station": "Sentrum",
    "eoi": "NO0113A",
    "component": "PM2.5",
    "fromTime": "2019-04-25T00:00:00+01:00",
    "toTime": "2019-04-25T01:00:00+01:00",
    "value": 13.685742,
    "unit": "µg/m³",
    "latitude": 68.435397,
    "longitude": 17.424891,
    "timestep": 3600,
    "index": 1,
    "color": "6ee86e"
  },
  {
    "zone": "Bergen",
    "municipality": "Bergen",
    "area": "Bergen",
    "station": "Rolland, Åsane",
    "eoi": "NO0108A",
    "component": "PM2.5",
    "fromTime": "2019-04-25T00:00:00+01:00",
    "toTime": "2019-04-25T01:00:00+01:00",
    "value": 11.609392,
    "unit": "µg/m³",
    "latitude": 60.462665,
    "longitude": 5.332447,
    "timestep": 3600,
    "index": 1,
    "color": "6ee86e"
  },
  {
    "zone": "Bergen",
    "municipality": "Bergen",
    "area": "Bergen",
    "station": "Loddefjord",
    "eoi": "NO0109A",
    "component": "PM2.5",
    "fromTime": "2019-04-25T00:00:00+01:00",
    "toTime": "2019-04-25T01:00:00+01:00",
    "value": 9.317286,
    "unit": "µg/m³",
    "latitude": 60.361135,
    "longitude": 5.23686,
    "timestep": 3600,
    "index": 1,
    "color": "6ee86e"
  },
  {
    "zone": "Stor-Oslo",
    "municipality": "Bærum",
    "area": "Bærum",
    "station": "Eilif Dues vei",
    "eoi": "NO0099A",
    "component": "PM2.5",
    "fromTime": "2019-04-25T00:00:00+01:00",
    "toTime": "2019-04-25T01:00:00+01:00",
    "value": 29.6,
    "unit": "µg/m³",
    "latitude": 59.90608,
    "longitude": 10.61195,
    "timestep": 3600,
    "index": 1,
    "color": "6ee86e"
  },
  {
    "zone": "Stor-Oslo",
    "municipality": "Skedsmo",
    "area": "Lillestrøm",
    "station": "Vigernes",
    "eoi": "NO0111A",
    "component": "PM2.5",
    "fromTime": "2019-04-25T00:00:00+01:00",
    "toTime": "2019-04-25T01:00:00+01:00",
    "value": 2.49518,
    "unit": "µg/m³",
    "latitude": 59.955477,
    "longitude": 11.073983,
    "timestep": 3600,
    "index": 1,
    "color": "6ee86e"
  },
  {
    "zone": "Øst og Sørlandet",
    "municipality": "Gjøvik",
    "area": "Gjøvik",
    "station": "Minnesundvegen, Gjøvik",
    "eoi": "NO0103A",
    "component": "PM2.5",
    "fromTime": "2019-04-25T00:00:00+01:00",
    "toTime": "2019-04-25T01:00:00+01:00",
    "value": 20.844372,
    "unit": "µg/m³",
    "latitude": 60.79089,
    "longitude": 10.6967,
    "timestep": 3600,
    "index": 1,
    "color": "6ee86e"
  },
  {
    "zone": "Trondheim",
    "municipality": "Trondheim",
    "area": "Trondheim",
    "station": "Elgeseter",
    "eoi": "NO0060A",
    "component": "PM2.5",
    "fromTime": "2019-04-25T00:00:00+01:00",
    "toTime": "2019-04-25T01:00:00+01:00",
    "value": 15.889612,
    "unit": "µg/m³",
    "latitude": 63.419239,
    "longitude": 10.395945,
    "timestep": 3600,
    "index": 1,
    "color": "6ee86e"
  },
  {
    "zone": "Øst og Sørlandet",
    "municipality": "Fredrikstad",
    "area": "Fredrikstad",
    "station": "St.Croix",
    "eoi": "NO0084A",
    "component": "PM2.5",
    "fromTime": "2019-04-25T00:00:00+01:00",
    "toTime": "2019-04-25T01:00:00+01:00",
    "value": 15.5,
    "unit": "µg/m³",
    "latitude": 59.2103,
    "longitude": 10.9454,
    "timestep": 3600,
    "index": 1,
    "color": "6ee86e"
  },
  {
    "zone": "Trondheim",
    "municipality": "Trondheim",
    "area": "Trondheim",
    "station": "E6-Tiller",
    "eoi": "NO0102A",
    "component": "PM2.5",
    "fromTime": "2019-04-25T00:00:00+01:00",
    "toTime": "2019-04-25T01:00:00+01:00",
    "value": 15.504159,
    "unit": "µg/m³",
    "latitude": 63.3576,
    "longitude": 10.3719,
    "timestep": 3600,
    "index": 1,
    "color": "6ee86e"
  },
  {
    "zone": "Trondheim",
    "municipality": "Trondheim",
    "area": "Trondheim",
    "station": "Bakke kirke",
    "eoi": "NO0068A",
    "component": "PM2.5",
    "fromTime": "2019-04-25T00:00:00+01:00",
    "toTime": "2019-04-25T01:00:00+01:00",
    "value": 14.991747,
    "unit": "µg/m³",
    "latitude": 63.43293,
    "longitude": 10.41067,
    "timestep": 3600,
    "index": 1,
    "color": "6ee86e"
  },
  {
    "zone": "Øst og Sørlandet",
    "municipality": "Moss",
    "area": "Moss",
    "station": "Kransen",
    "eoi": "NO0112A",
    "component": "PM2.5",
    "fromTime": "2019-04-25T00:00:00+01:00",
    "toTime": "2019-04-25T01:00:00+01:00",
    "value": 20.108,
    "unit": "µg/m³",
    "latitude": 59.433471,
    "longitude": 10.66176236,
    "timestep": 3600,
    "index": 1,
    "color": "6ee86e"
  },
  {
    "zone": "Øst og Sørlandet",
    "municipality": "Grenland",
    "area": "Grenland",
    "station": "Lensmannsdalen",
    "eoi": "NO0061A",
    "component": "PM2.5",
    "fromTime": "2019-04-25T00:00:00+01:00",
    "toTime": "2019-04-25T01:00:00+01:00",
    "value": 14.6,
    "unit": "µg/m³",
    "latitude": 59.15927,
    "longitude": 9.63565,
    "timestep": 3600,
    "index": 1,
    "color": "6ee86e"
  },
  {
    "zone": "Øst og Sørlandet",
    "municipality": "Lillehammer",
    "area": "Lillehammer",
    "station": "Bankplassen",
    "eoi": "NO0074A",
    "component": "PM2.5",
    "fromTime": "2019-04-25T00:00:00+01:00",
    "toTime": "2019-04-25T01:00:00+01:00",
    "value": 18,
    "unit": "µg/m³",
    "latitude": 61.11288,
    "longitude": 10.46497,
    "timestep": 3600,
    "index": 1,
    "color": "6ee86e"
  },
  {
    "zone": "Troms og Finnmark",
    "municipality": "Tromsø",
    "area": "Tromsø",
    "station": "Hansjordnesbukta",
    "eoi": "NO0079A",
    "component": "PM2.5",
    "fromTime": "2019-04-25T00:00:00+01:00",
    "toTime": "2019-04-25T01:00:00+01:00",
    "value": 10.1,
    "unit": "µg/m³",
    "latitude": 69.65625,
    "longitude": 18.96372,
    "timestep": 3600,
    "index": 1,
    "color": "6ee86e"
  },
  {
    "zone": "Stor-Oslo",
    "municipality": "Oslo",
    "area": "Oslo",
    "station": "Kirkeveien",
    "eoi": "NO0011A",
    "component": "PM2.5",
    "fromTime": "2019-04-25T00:00:00+01:00",
    "toTime": "2019-04-25T01:00:00+01:00",
    "value": 24.693041,
    "unit": "µg/m³",
    "latitude": 59.93233,
    "longitude": 10.72447,
    "timestep": 3600,
    "index": 1,
    "color": "6ee86e"
  },
  {
    "zone": "Stor-Oslo",
    "municipality": "Oslo",
    "area": "Oslo",
    "station": "Manglerud",
    "eoi": "NO0071A",
    "component": "PM2.5",
    "fromTime": "2019-04-25T00:00:00+01:00",
    "toTime": "2019-04-25T01:00:00+01:00",
    "value": 23.3,
    "unit": "µg/m³",
    "latitude": 59.89869,
    "longitude": 10.81495,
    "timestep": 3600,
    "index": 1,
    "color": "6ee86e"
  },
  {
    "zone": "Bergen",
    "municipality": "Bergen",
    "area": "Bergen",
    "station": "Danmarks plass",
    "eoi": "NO0059A",
    "component": "PM2.5",
    "fromTime": "2019-04-25T00:00:00+01:00",
    "toTime": "2019-04-25T01:00:00+01:00",
    "value": 10.707181,
    "unit": "µg/m³",
    "latitude": 60.37408,
    "longitude": 5.34042,
    "timestep": 3600,
    "index": 1,
    "color": "6ee86e"
  },
  {
    "zone": "Øst og Sørlandet",
    "municipality": "Lillehammer",
    "area": "Lillehammer",
    "station": "Lillehammer barnehage",
    "eoi": "NO0075A",
    "component": "PM2.5",
    "fromTime": "2019-04-25T00:00:00+01:00",
    "toTime": "2019-04-25T01:00:00+01:00",
    "value": 17.859167,
    "unit": "µg/m³",
    "latitude": 61.12087,
    "longitude": 10.46563,
    "timestep": 3600,
    "index": 1,
    "color": "6ee86e"
  },
  {
    "zone": "Stor-Oslo",
    "municipality": "Oslo",
    "area": "Oslo",
    "station": "Rv 4, Aker sykehus",
    "eoi": "NO0101A",
    "component": "PM2.5",
    "fromTime": "2019-04-25T00:00:00+01:00",
    "toTime": "2019-04-25T01:00:00+01:00",
    "value": 25.151984,
    "unit": "µg/m³",
    "latitude": 59.94103,
    "longitude": 10.79803,
    "timestep": 3600,
    "index": 1,
    "color": "6ee86e"
  },
  {
    "zone": "Vestlandet",
    "municipality": "Stavanger",
    "area": "Stavanger",
    "station": "Kannik",
    "eoi": "NO0076A",
    "component": "PM2.5",
    "fromTime": "2019-04-25T00:00:00+01:00",
    "toTime": "2019-04-25T01:00:00+01:00",
    "value": 15.9,
    "unit": "µg/m³",
    "latitude": 58.96415,
    "longitude": 5.72785,
    "timestep": 3600,
    "index": 1,
    "color": "6ee86e"
  },
  {
    "zone": "Stor-Oslo",
    "municipality": "Oslo",
    "area": "Oslo",
    "station": "Hjortnes",
    "eoi": "NO0093A",
    "component": "PM2.5",
    "fromTime": "2019-04-25T00:00:00+01:00",
    "toTime": "2019-04-25T01:00:00+01:00",
    "value": 25.2,
    "unit": "µg/m³",
    "latitude": 59.91132,
    "longitude": 10.70407,
    "timestep": 3600,
    "index": 1,
    "color": "6ee86e"
  },
  {
    "zone": "Stor-Oslo",
    "municipality": "Oslo",
    "area": "Oslo",
    "station": "E6 Alna senter",
    "eoi": "NO0122A",
    "component": "PM2.5",
    "fromTime": "2019-04-25T00:00:00+01:00",
    "toTime": "2019-04-25T01:00:00+01:00",
    "value": 31.223361,
    "unit": "µg/m³",
    "latitude": 59.92556,
    "longitude": 10.850367,
    "timestep": 3600,
    "index": 2,
    "color": "ff9900"
  },
  {
    "zone": "Stor-Oslo",
    "municipality": "Bærum",
    "area": "Bærum",
    "station": "Bekkestua",
    "eoi": "NO0114A",
    "component": "PM2.5",
    "fromTime": "2019-04-25T00:00:00+01:00",
    "toTime": "2019-04-25T01:00:00+01:00",
    "value": 33.6,
    "unit": "µg/m³",
    "latitude": 59.9181,
    "longitude": 10.5839,
    "timestep": 3600,
    "index": 2,
    "color": "ff9900"
  },
  {
    "zone": "Stor-Oslo",
    "municipality": "Oslo",
    "area": "Oslo",
    "station": "Bygdøy Alle",
    "eoi": "NO0083A",
    "component": "PM2.5",
    "fromTime": "2019-04-25T00:00:00+01:00",
    "toTime": "2019-04-25T01:00:00+01:00",
    "value": 31.6,
    "unit": "µg/m³",
    "latitude": 59.91898,
    "longitude": 10.69707,
    "timestep": 3600,
    "index": 2,
    "color": "ff9900"
  },
  {
    "zone": "Trondheim",
    "municipality": "Trondheim",
    "area": "Trondheim",
    "station": "Elgeseter",
    "eoi": "NO0060A",
    "component": "NO2",
    "fromTime": "2019-04-25T00:00:00+01:00",
    "toTime": "2019-04-25T01:00:00+01:00",
    "value": 6.271927,
    "unit": "µg/m³",
    "latitude": 63.419239,
    "longitude": 10.395945,
    "timestep": 3600,
    "index": 1,
    "color": "6ee86e"
  },
  {
    "zone": "Vestlandet",
    "municipality": "Stavanger",
    "area": "Stavanger",
    "station": "Schancheholen",
    "eoi": "NO0125A",
    "component": "NO2",
    "fromTime": "2019-04-25T00:00:00+01:00",
    "toTime": "2019-04-25T01:00:00+01:00",
    "value": 5.410088,
    "unit": "µg/m³",
    "latitude": 58.951877,
    "longitude": 5.721875,
    "timestep": 3600,
    "index": 1,
    "color": "6ee86e"
  },
  {
    "zone": "Stor-Oslo",
    "municipality": "Oslo",
    "area": "Oslo",
    "station": "Bryn skole",
    "eoi": null,
    "component": "NO2",
    "fromTime": "2019-04-25T01:00:00+01:00",
    "toTime": "2019-04-25T02:00:00+01:00",
    "value": 3.602741,
    "unit": "µg/m³",
    "latitude": 59.914106,
    "longitude": 10.82263,
    "timestep": 3600,
    "index": 1,
    "color": "6ee86e"
  },
  {
    "zone": "Øst og Sørlandet",
    "municipality": "N/A",
    "area": "Hønefoss",
    "station": "Hønefoss skole",
    "eoi": null,
    "component": "NO2",
    "fromTime": "2019-04-25T00:00:00+01:00",
    "toTime": "2019-04-25T01:00:00+01:00",
    "value": 4.123216,
    "unit": "µg/m³",
    "latitude": 60.170873,
    "longitude": 10.261552,
    "timestep": 3600,
    "index": 1,
    "color": "6ee86e"
  },
  {
    "zone": "Øst og Sørlandet",
    "municipality": "N/A",
    "area": "Brumunddal",
    "station": "Ringsakervegen",
    "eoi": null,
    "component": "NO2",
    "fromTime": "2019-04-25T00:00:00+01:00",
    "toTime": "2019-04-25T01:00:00+01:00",
    "value": 3.166458,
    "unit": "µg/m³",
    "latitude": 60.88593,
    "longitude": 10.93785,
    "timestep": 3600,
    "index": 1,
    "color": "6ee86e"
  },
  {
    "zone": "Stor-Oslo",
    "municipality": "Oslo",
    "area": "Oslo",
    "station": "E6 Alna senter",
    "eoi": "NO0122A",
    "component": "NO2",
    "fromTime": "2019-04-25T00:00:00+01:00",
    "toTime": "2019-04-25T01:00:00+01:00",
    "value": 11.980059,
    "unit": "µg/m³",
    "latitude": 59.92556,
    "longitude": 10.850367,
    "timestep": 3600,
    "index": 1,
    "color": "6ee86e"
  },
  {
    "zone": "Troms og Finnmark",
    "municipality": "Harstad",
    "area": "Harstad",
    "station": "Seljestad Rv83",
    "eoi": null,
    "component": "NO2",
    "fromTime": "2019-04-25T00:00:00+01:00",
    "toTime": "2019-04-25T01:00:00+01:00",
    "value": 16.344519,
    "unit": "µg/m³",
    "latitude": 68.79222701,
    "longitude": 16.53742346,
    "timestep": 3600,
    "index": 1,
    "color": "6ee86e"
  },
  {
    "zone": "Øst og Sørlandet",
    "municipality": "Lørenskog",
    "area": "Lørenskog",
    "station": "Solheim",
    "eoi": null,
    "component": "NO2",
    "fromTime": "2019-04-25T00:00:00+01:00",
    "toTime": "2019-04-25T01:00:00+01:00",
    "value": 8.496287,
    "unit": "µg/m³",
    "latitude": 59.928612,
    "longitude": 10.953203,
    "timestep": 3600,
    "index": 1,
    "color": "6ee86e"
  },
  {
    "zone": "Bergen",
    "municipality": "Bergen",
    "area": "Bergen",
    "station": "Rolland, Åsane",
    "eoi": "NO0108A",
    "component": "NO2",
    "fromTime": "2019-04-25T00:00:00+01:00",
    "toTime": "2019-04-25T01:00:00+01:00",
    "value": 5.645748,
    "unit": "µg/m³",
    "latitude": 60.462665,
    "longitude": 5.332447,
    "timestep": 3600,
    "index": 1,
    "color": "6ee86e"
  },
  {
    "zone": "Stor-Oslo",
    "municipality": "Bærum",
    "area": "Bærum",
    "station": "Eilif Dues vei",
    "eoi": "NO0099A",
    "component": "NO2",
    "fromTime": "2019-04-25T00:00:00+01:00",
    "toTime": "2019-04-25T01:00:00+01:00",
    "value": 17.093947,
    "unit": "µg/m³",
    "latitude": 59.90608,
    "longitude": 10.61195,
    "timestep": 3600,
    "index": 1,
    "color": "6ee86e"
  },
  {
    "zone": "Trondheim",
    "municipality": "Trondheim",
    "area": "Trondheim",
    "station": "E6-Tiller",
    "eoi": "NO0102A",
    "component": "NO2",
    "fromTime": "2019-04-25T00:00:00+01:00",
    "toTime": "2019-04-25T01:00:00+01:00",
    "value": 4.752117,
    "unit": "µg/m³",
    "latitude": 63.3576,
    "longitude": 10.3719,
    "timestep": 3600,
    "index": 1,
    "color": "6ee86e"
  },
  {
    "zone": "Bergen",
    "municipality": "Bergen",
    "area": "Bergen",
    "station": "Klosterhaugen",
    "eoi": "NO0120A",
    "component": "NO2",
    "fromTime": "2019-04-25T00:00:00+01:00",
    "toTime": "2019-04-25T01:00:00+01:00",
    "value": 38.886462,
    "unit": "µg/m³",
    "latitude": 60.395929,
    "longitude": 5.312674,
    "timestep": 3600,
    "index": 1,
    "color": "6ee86e"
  },
  {
    "zone": "Øst og Sørlandet",
    "municipality": "Moss",
    "area": "Moss",
    "station": "Kransen",
    "eoi": "NO0112A",
    "component": "NO2",
    "fromTime": "2019-04-25T00:00:00+01:00",
    "toTime": "2019-04-25T01:00:00+01:00",
    "value": 4.42119,
    "unit": "µg/m³",
    "latitude": 59.433471,
    "longitude": 10.66176236,
    "timestep": 3600,
    "index": 1,
    "color": "6ee86e"
  },
  {
    "zone": "Bergen",
    "municipality": "Bergen",
    "area": "Bergen",
    "station": "Rådal",
    "eoi": "NO0121A",
    "component": "NO2",
    "fromTime": "2019-04-25T00:00:00+01:00",
    "toTime": "2019-04-25T01:00:00+01:00",
    "value": 9.054887,
    "unit": "µg/m³",
    "latitude": 60.294268,
    "longitude": 5.324619,
    "timestep": 3600,
    "index": 1,
    "color": "6ee86e"
  },
  {
    "zone": "Bergen",
    "municipality": "Bergen",
    "area": "Bergen",
    "station": "Loddefjord",
    "eoi": "NO0109A",
    "component": "NO2",
    "fromTime": "2019-04-25T00:00:00+01:00",
    "toTime": "2019-04-25T01:00:00+01:00",
    "value": 14.022021,
    "unit": "µg/m³",
    "latitude": 60.361135,
    "longitude": 5.23686,
    "timestep": 3600,
    "index": 1,
    "color": "6ee86e"
  },
  {
    "zone": "Øst og Sørlandet",
    "municipality": "Gjøvik",
    "area": "Gjøvik",
    "station": "Minnesundvegen, Gjøvik",
    "eoi": "NO0103A",
    "component": "NO2",
    "fromTime": "2019-04-25T00:00:00+01:00",
    "toTime": "2019-04-25T01:00:00+01:00",
    "value": 18.438266,
    "unit": "µg/m³",
    "latitude": 60.79089,
    "longitude": 10.6967,
    "timestep": 3600,
    "index": 1,
    "color": "6ee86e"
  },
  {
    "zone": "Øst og Sørlandet",
    "municipality": "Lillehammer",
    "area": "Lillehammer",
    "station": "Lillehammer barnehage",
    "eoi": "NO0075A",
    "component": "NO2",
    "fromTime": "2019-04-25T00:00:00+01:00",
    "toTime": "2019-04-25T01:00:00+01:00",
    "value": 1.515135,
    "unit": "µg/m³",
    "latitude": 61.12087,
    "longitude": 10.46563,
    "timestep": 3600,
    "index": 1,
    "color": "6ee86e"
  },
  {
    "zone": "Øst og Sørlandet",
    "municipality": "Grenland",
    "area": "Grenland",
    "station": "Sverresgate",
    "eoi": "NO0106A",
    "component": "NO2",
    "fromTime": "2019-04-25T00:00:00+01:00",
    "toTime": "2019-04-25T01:00:00+01:00",
    "value": 3.629761,
    "unit": "µg/m³",
    "latitude": 59.13812,
    "longitude": 9.65212,
    "timestep": 3600,
    "index": 1,
    "color": "6ee86e"
  },
  {
    "zone": "Stor-Oslo",
    "municipality": "Oslo",
    "area": "Oslo",
    "station": "Kirkeveien",
    "eoi": "NO0011A",
    "component": "NO2",
    "fromTime": "2019-04-25T00:00:00+01:00",
    "toTime": "2019-04-25T01:00:00+01:00",
    "value": 7.696046,
    "unit": "µg/m³",
    "latitude": 59.93233,
    "longitude": 10.72447,
    "timestep": 3600,
    "index": 1,
    "color": "6ee86e"
  },
  {
    "zone": "Stor-Oslo",
    "municipality": "Oslo",
    "area": "Oslo",
    "station": "Bygdøy Alle",
    "eoi": "NO0083A",
    "component": "NO2",
    "fromTime": "2019-04-25T00:00:00+01:00",
    "toTime": "2019-04-25T01:00:00+01:00",
    "value": 9.678163,
    "unit": "µg/m³",
    "latitude": 59.91898,
    "longitude": 10.69707,
    "timestep": 3600,
    "index": 1,
    "color": "6ee86e"
  },
  {
    "zone": "Øst og Sørlandet",
    "municipality": "Grenland",
    "area": "Grenland",
    "station": "Knarrdalstranda",
    "eoi": "NO0118A",
    "component": "NO2",
    "fromTime": "2019-04-25T00:00:00+01:00",
    "toTime": "2019-04-25T01:00:00+01:00",
    "value": 2.503941,
    "unit": "µg/m³",
    "latitude": 59.13354,
    "longitude": 9.6219,
    "timestep": 3600,
    "index": 1,
    "color": "6ee86e"
  },
  {
    "zone": "Midt-Norge og Nordland",
    "municipality": "Ålesund",
    "area": "Ålesund",
    "station": "Karl Eriksens plass",
    "eoi": "NO0116A",
    "component": "NO2",
    "fromTime": "2019-04-25T00:00:00+01:00",
    "toTime": "2019-04-25T01:00:00+01:00",
    "value": 39.7851,
    "unit": "µg/m³",
    "latitude": 62.470622,
    "longitude": 6.153501,
    "timestep": 3600,
    "index": 1,
    "color": "6ee86e"
  },
  {
    "zone": "Øst og Sørlandet",
    "municipality": "Elverum",
    "area": "Elverum",
    "station": "Leiret",
    "eoi": "NO0119A",
    "component": "NO2",
    "fromTime": "2019-04-25T00:00:00+01:00",
    "toTime": "2019-04-25T01:00:00+01:00",
    "value": 2.782392,
    "unit": "µg/m³",
    "latitude": 60.88364255,
    "longitude": 11.55930063,
    "timestep": 3600,
    "index": 1,
    "color": "6ee86e"
  },
  {
    "zone": "Øst og Sørlandet",
    "municipality": "Grenland",
    "area": "Grenland",
    "station": "Furulund",
    "eoi": "NO0115A",
    "component": "NO2",
    "fromTime": "2019-04-25T00:00:00+01:00",
    "toTime": "2019-04-25T01:00:00+01:00",
    "value": 2.911795,
    "unit": "µg/m³",
    "latitude": 59.057304,
    "longitude": 9.695568,
    "timestep": 3600,
    "index": 1,
    "color": "6ee86e"
  },
  {
    "zone": "Stor-Oslo",
    "municipality": "Bærum",
    "area": "Bærum",
    "station": "Bekkestua",
    "eoi": "NO0114A",
    "component": "NO2",
    "fromTime": "2019-04-25T00:00:00+01:00",
    "toTime": "2019-04-25T01:00:00+01:00",
    "value": 7.976775,
    "unit": "µg/m³",
    "latitude": 59.9181,
    "longitude": 10.5839,
    "timestep": 3600,
    "index": 1,
    "color": "6ee86e"
  },
  {
    "zone": "Stor-Oslo",
    "municipality": "Skedsmo",
    "area": "Lillestrøm",
    "station": "Vigernes",
    "eoi": "NO0111A",
    "component": "NO2",
    "fromTime": "2019-04-25T00:00:00+01:00",
    "toTime": "2019-04-25T01:00:00+01:00",
    "value": 2.471708,
    "unit": "µg/m³",
    "latitude": 59.955477,
    "longitude": 11.073983,
    "timestep": 3600,
    "index": 1,
    "color": "6ee86e"
  },
  {
    "zone": "Øst og Sørlandet",
    "municipality": "Hamar",
    "area": "Hamar",
    "station": "Vangsveien, Hamar",
    "eoi": "NO0104A",
    "component": "NO2",
    "fromTime": "2019-04-25T00:00:00+01:00",
    "toTime": "2019-04-25T01:00:00+01:00",
    "value": 8.668172,
    "unit": "µg/m³",
    "latitude": 60.79646,
    "longitude": 11.09777,
    "timestep": 3600,
    "index": 1,
    "color": "6ee86e"
  },
  {
    "zone": "Vestlandet",
    "municipality": "Stavanger",
    "area": "Stavanger",
    "station": "Våland",
    "eoi": "NO0065A",
    "component": "NO2",
    "fromTime": "2019-04-25T00:00:00+01:00",
    "toTime": "2019-04-25T01:00:00+01:00",
    "value": 3.639458,
    "unit": "µg/m³",
    "latitude": 58.96173,
    "longitude": 5.73147,
    "timestep": 3600,
    "index": 1,
    "color": "6ee86e"
  },
  {
    "zone": "Stor-Oslo",
    "municipality": "Oslo",
    "area": "Oslo",
    "station": "Hjortnes",
    "eoi": "NO0093A",
    "component": "NO2",
    "fromTime": "2019-04-25T00:00:00+01:00",
    "toTime": "2019-04-25T01:00:00+01:00",
    "value": 17.097032,
    "unit": "µg/m³",
    "latitude": 59.91132,
    "longitude": 10.70407,
    "timestep": 3600,
    "index": 1,
    "color": "6ee86e"
  },
  {
    "zone": "Øst og Sørlandet",
    "municipality": "Kristiansand",
    "area": "Kristiansand",
    "station": "Gartnerløkka",
    "eoi": "NO0092A",
    "component": "NO2",
    "fromTime": "2019-04-25T00:00:00+01:00",
    "toTime": "2019-04-25T01:00:00+01:00",
    "value": 14.84089,
    "unit": "µg/m³",
    "latitude": 58.14703,
    "longitude": 7.98662,
    "timestep": 3600,
    "index": 1,
    "color": "6ee86e"
  },
  {
    "zone": "Stor-Oslo",
    "municipality": "Oslo",
    "area": "Oslo",
    "station": "Alnabru",
    "eoi": "NO0057A",
    "component": "NO2",
    "fromTime": "2019-04-25T00:00:00+01:00",
    "toTime": "2019-04-25T01:00:00+01:00",
    "value": 12.044818,
    "unit": "µg/m³",
    "latitude": 59.92773,
    "longitude": 10.84633,
    "timestep": 3600,
    "index": 1,
    "color": "6ee86e"
  },
  {
    "zone": "Stor-Oslo",
    "municipality": "Oslo",
    "area": "Oslo",
    "station": "Rv 4, Aker sykehus",
    "eoi": "NO0101A",
    "component": "NO2",
    "fromTime": "2019-04-25T00:00:00+01:00",
    "toTime": "2019-04-25T01:00:00+01:00",
    "value": 7.617399,
    "unit": "µg/m³",
    "latitude": 59.94103,
    "longitude": 10.79803,
    "timestep": 3600,
    "index": 1,
    "color": "6ee86e"
  },
  {
    "zone": "Trondheim",
    "municipality": "Trondheim",
    "area": "Trondheim",
    "station": "Bakke kirke",
    "eoi": "NO0068A",
    "component": "NO2",
    "fromTime": "2019-04-25T00:00:00+01:00",
    "toTime": "2019-04-25T01:00:00+01:00",
    "value": 3.211011,
    "unit": "µg/m³",
    "latitude": 63.43293,
    "longitude": 10.41067,
    "timestep": 3600,
    "index": 1,
    "color": "6ee86e"
  },
  {
    "zone": "Troms og Finnmark",
    "municipality": "Tromsø",
    "area": "Tromsø",
    "station": "Hansjordnesbukta",
    "eoi": "NO0079A",
    "component": "NO2",
    "fromTime": "2019-04-25T00:00:00+01:00",
    "toTime": "2019-04-25T01:00:00+01:00",
    "value": 53.344252,
    "unit": "µg/m³",
    "latitude": 69.65625,
    "longitude": 18.96372,
    "timestep": 3600,
    "index": 1,
    "color": "6ee86e"
  },
  {
    "zone": "Stor-Oslo",
    "municipality": "Oslo",
    "area": "Oslo",
    "station": "Smestad",
    "eoi": "NO0095A",
    "component": "NO2",
    "fromTime": "2019-04-25T00:00:00+01:00",
    "toTime": "2019-04-25T01:00:00+01:00",
    "value": 12.801408,
    "unit": "µg/m³",
    "latitude": 59.93255,
    "longitude": 10.66984,
    "timestep": 3600,
    "index": 1,
    "color": "6ee86e"
  },
  {
    "zone": "Øst og Sørlandet",
    "municipality": "Fredrikstad",
    "area": "Fredrikstad",
    "station": "St.Croix",
    "eoi": "NO0084A",
    "component": "NO2",
    "fromTime": "2019-04-25T00:00:00+01:00",
    "toTime": "2019-04-25T01:00:00+01:00",
    "value": 3.241397,
    "unit": "µg/m³",
    "latitude": 59.2103,
    "longitude": 10.9454,
    "timestep": 3600,
    "index": 1,
    "color": "6ee86e"
  },
  {
    "zone": "Øst og Sørlandet",
    "municipality": "Grenland",
    "area": "Grenland",
    "station": "Lensmannsdalen",
    "eoi": "NO0061A",
    "component": "NO2",
    "fromTime": "2019-04-25T00:00:00+01:00",
    "toTime": "2019-04-25T01:00:00+01:00",
    "value": 3.728964,
    "unit": "µg/m³",
    "latitude": 59.15927,
    "longitude": 9.63565,
    "timestep": 3600,
    "index": 1,
    "color": "6ee86e"
  },
  {
    "zone": "Øst og Sørlandet",
    "municipality": "Kristiansand",
    "area": "Kristiansand",
    "station": "Stener Heyerdahl",
    "eoi": "NO0063A",
    "component": "NO2",
    "fromTime": "2019-04-25T00:00:00+01:00",
    "toTime": "2019-04-25T01:00:00+01:00",
    "value": 3.967508,
    "unit": "µg/m³",
    "latitude": 58.14888,
    "longitude": 7.99183,
    "timestep": 3600,
    "index": 1,
    "color": "6ee86e"
  },
  {
    "zone": "Stor-Oslo",
    "municipality": "Oslo",
    "area": "Oslo",
    "station": "Manglerud",
    "eoi": "NO0071A",
    "component": "NO2",
    "fromTime": "2019-04-25T00:00:00+01:00",
    "toTime": "2019-04-25T01:00:00+01:00",
    "value": 3.523842,
    "unit": "µg/m³",
    "latitude": 59.89869,
    "longitude": 10.81495,
    "timestep": 3600,
    "index": 1,
    "color": "6ee86e"
  },
  {
    "zone": "Øst og Sørlandet",
    "municipality": "Lillehammer",
    "area": "Lillehammer",
    "station": "Bankplassen",
    "eoi": "NO0074A",
    "component": "NO2",
    "fromTime": "2019-04-25T00:00:00+01:00",
    "toTime": "2019-04-25T01:00:00+01:00",
    "value": 3.757008,
    "unit": "µg/m³",
    "latitude": 61.11288,
    "longitude": 10.46497,
    "timestep": 3600,
    "index": 1,
    "color": "6ee86e"
  },
  {
    "zone": "Bergen",
    "municipality": "Bergen",
    "area": "Bergen",
    "station": "Danmarks plass",
    "eoi": "NO0059A",
    "component": "NO2",
    "fromTime": "2019-04-25T00:00:00+01:00",
    "toTime": "2019-04-25T01:00:00+01:00",
    "value": 3.227646,
    "unit": "µg/m³",
    "latitude": 60.37408,
    "longitude": 5.34042,
    "timestep": 3600,
    "index": 1,
    "color": "6ee86e"
  },
  {
    "zone": "Øst og Sørlandet",
    "municipality": "Grenland",
    "area": "Grenland",
    "station": "Haukenes",
    "eoi": "NO0062A",
    "component": "NO2",
    "fromTime": "2019-04-25T00:00:00+01:00",
    "toTime": "2019-04-25T01:00:00+01:00",
    "value": 4.63652,
    "unit": "µg/m³",
    "latitude": 59.2024,
    "longitude": 9.48708,
    "timestep": 3600,
    "index": 1,
    "color": "6ee86e"
  },
  {
    "zone": "Vestlandet",
    "municipality": "Stavanger",
    "area": "Stavanger",
    "station": "Kannik",
    "eoi": "NO0076A",
    "component": "NO2",
    "fromTime": "2019-04-25T00:00:00+01:00",
    "toTime": "2019-04-25T01:00:00+01:00",
    "value": 4.72671,
    "unit": "µg/m³",
    "latitude": 58.96415,
    "longitude": 5.72785,
    "timestep": 3600,
    "index": 1,
    "color": "6ee86e"
  },
  {
    "zone": "Stor-Oslo",
    "municipality": "Oslo",
    "area": "Oslo",
    "station": "Åkebergveien",
    "eoi": null,
    "component": "NO2",
    "fromTime": "2019-04-25T00:00:00+01:00",
    "toTime": "2019-04-25T01:00:00+01:00",
    "value": 6.416812,
    "unit": "µg/m³",
    "latitude": 59.912001,
    "longitude": 10.767426,
    "timestep": 3600,
    "index": 1,
    "color": "6ee86e"
  },
  {
    "zone": "Stor-Oslo",
    "municipality": "Drammen",
    "area": "Drammen",
    "station": "Bangeløkka",
    "eoi": "NO0067A",
    "component": "NO2",
    "fromTime": "2019-04-25T00:00:00+01:00",
    "toTime": "2019-04-25T01:00:00+01:00",
    "value": 8.110099,
    "unit": "µg/m³",
    "latitude": 59.73325,
    "longitude": 10.21187,
    "timestep": 3600,
    "index": 1,
    "color": "6ee86e"
  },
  {
    "zone": "Utenfor sonesystemet",
    "municipality": "Svalbard",
    "area": "Zeppelinfjellet",
    "station": "Zeppelinfjellet",
    "eoi": "NO0042R",
    "component": "O3",
    "fromTime": "2019-04-25T00:00:00+01:00",
    "toTime": "2019-04-25T01:00:00+01:00",
    "value": 81.8,
    "unit": "µg/m³",
    "latitude": 78.90669,
    "longitude": 11.88899,
    "timestep": 3600,
    "index": 1,
    "color": "6ee86e"
  },
  {
    "zone": "Øst og Sørlandet",
    "municipality": "Grenland",
    "area": "Grenland",
    "station": "Haukenes",
    "eoi": "NO0062A",
    "component": "O3",
    "fromTime": "2019-04-25T00:00:00+01:00",
    "toTime": "2019-04-25T01:00:00+01:00",
    "value": 74.2,
    "unit": "µg/m³",
    "latitude": 59.2024,
    "longitude": 9.48708,
    "timestep": 3600,
    "index": 1,
    "color": "6ee86e"
  },
  {
    "zone": "Øst og Sørlandet",
    "municipality": "Birkenes",
    "area": "Birkenes",
    "station": "Birkenesobservatoriet",
    "eoi": "NO0002R",
    "component": "O3",
    "fromTime": "2019-04-25T00:00:00+01:00",
    "toTime": "2019-04-25T01:00:00+01:00",
    "value": 95.85,
    "unit": "µg/m³",
    "latitude": 58.38846,
    "longitude": 8.2519,
    "timestep": 3600,
    "index": 1,
    "color": "6ee86e"
  },
  {
    "zone": "Vestlandet",
    "municipality": "Karmøy",
    "area": "Sandve",
    "station": "Sandve",
    "eoi": "NO0052R",
    "component": "O3",
    "fromTime": "2019-04-25T00:00:00+01:00",
    "toTime": "2019-04-25T01:00:00+01:00",
    "value": 82.6,
    "unit": "µg/m³",
    "latitude": 59.19722,
    "longitude": 5.20148,
    "timestep": 3600,
    "index": 1,
    "color": "6ee86e"
  },
  {
    "zone": "Stor-Oslo",
    "municipality": "Oslo",
    "area": "Oslo",
    "station": "Sofienbergparken",
    "eoi": "NO0073A",
    "component": "O3",
    "fromTime": "2019-04-25T00:00:00+01:00",
    "toTime": "2019-04-25T01:00:00+01:00",
    "value": 119.6,
    "unit": "µg/m³",
    "latitude": 59.92295,
    "longitude": 10.76573,
    "timestep": 3600,
    "index": 2,
    "color": "ff9900"
  },
  {
    "zone": "Bergen",
    "municipality": "Bergen",
    "area": "Bergen",
    "station": "Klosterhaugen",
    "eoi": "NO0120A",
    "component": "O3",
    "fromTime": "2019-04-25T00:00:00+01:00",
    "toTime": "2019-04-25T01:00:00+01:00",
    "value": 108.754444,
    "unit": "µg/m³",
    "latitude": 60.395929,
    "longitude": 5.312674,
    "timestep": 3600,
    "index": 2,
    "color": "ff9900"
  },
  {
    "zone": "Øst og Sørlandet",
    "municipality": "Hurdal",
    "area": "Hurdal",
    "station": "Hurdal25",
    "eoi": "NO0056R",
    "component": "O3",
    "fromTime": "2019-04-25T00:00:00+01:00",
    "toTime": "2019-04-25T01:00:00+01:00",
    "value": 134.2,
    "unit": "µg/m³",
    "latitude": 60.37288,
    "longitude": 11.07407,
    "timestep": 3600,
    "index": 2,
    "color": "ff9900"
  },
  {
    "zone": "Midt-Norge og Nordland",
    "municipality": "Sunndal",
    "area": "Kårvatn",
    "station": "Kårvatn",
    "eoi": "NO0039R",
    "component": "O3",
    "fromTime": "2019-04-25T00:00:00+01:00",
    "toTime": "2019-04-25T01:00:00+01:00",
    "value": 122.2,
    "unit": "µg/m³",
    "latitude": 62.78246,
    "longitude": 8.87658,
    "timestep": 3600,
    "index": 2,
    "color": "ff9900"
  },
  {
    "zone": "Midt-Norge og Nordland",
    "municipality": "Hemnes",
    "area": "Tustervatn",
    "station": "Tustervatn",
    "eoi": "NO0015R",
    "component": "O3",
    "fromTime": "2019-04-25T00:00:00+01:00",
    "toTime": "2019-04-25T01:00:00+01:00",
    "value": 120,
    "unit": "µg/m³",
    "latitude": 65.83089,
    "longitude": 13.90655,
    "timestep": 3600,
    "index": 2,
    "color": "ff9900"
  },
  {
    "zone": "Øst og Sørlandet",
    "municipality": "Halden",
    "area": "Prestebakke",
    "station": "Prestebakke",
    "eoi": "NO0043R",
    "component": "O3",
    "fromTime": "2019-04-25T00:00:00+01:00",
    "toTime": "2019-04-25T01:00:00+01:00",
    "value": 120.8,
    "unit": "µg/m³",
    "latitude": 58.99677,
    "longitude": 11.52769,
    "timestep": 3600,
    "index": 2,
    "color": "ff9900"
  },
  {
    "zone": "Stor-Oslo",
    "municipality": "Bærum",
    "area": "Bærum",
    "station": "Lommedalen",
    "eoi": "NO0081A",
    "component": "O3",
    "fromTime": "2019-04-25T00:00:00+01:00",
    "toTime": "2019-04-25T01:00:00+01:00",
    "value": 125.427136,
    "unit": "µg/m³",
    "latitude": 59.9524,
    "longitude": 10.487777,
    "timestep": 3600,
    "index": 2,
    "color": "ff9900"
  }
]